openlane/watchdog_timer/src/watchdog_timer.v
`timescale 1ns/1ps

module watchdog_timer #(
    parameter TIMEOUT_WIDTH = 4
)(
    input  wire                     clk,
    input  wire                     rst,
    input  wire                     enable,
    input  wire                     kick,
    input  wire [TIMEOUT_WIDTH-1:0] timeout,

    output reg                      wdt_reset,
    output reg  [TIMEOUT_WIDTH-1:0] count
);

always @(posedge clk) begin
    if (rst) begin
        count     <= 0;
        wdt_reset <= 0;
    end
    else if (!enable) begin
        count     <= 0;
        wdt_reset <= 0;
    end
    else if (kick) begin
        count     <= 0;
        wdt_reset <= 0;
    end
    else if (count >= timeout) begin
        wdt_reset <= 1;
    end
    else begin
        count <= count + 1'b1;
        wdt_reset <= 0;
    end
end

endmodule

tb/tb.v
`timescale 1ns/1ps

module tb;

    reg clk;
    reg rst;
    reg enable;
    reg kick;
    reg [3:0] timeout;

    wire wdt_reset;
    wire [3:0] count;

    watchdog_timer #(
        .TIMEOUT_WIDTH(4)
    ) dut (
        .clk(clk),
        .rst(rst),
        .enable(enable),
        .kick(kick),
        .timeout(timeout),
        .wdt_reset(wdt_reset),
        .count(count)
    );

    // Clock: 10 ns period
    always #5 clk = ~clk;

    initial begin
        // Waveform dump
        $dumpfile("../sim/dump.vcd");
        $dumpvars(0, tb);

        // Initial values
        clk     = 0;
        rst     = 1;
        enable  = 0;
        kick    = 0;
        timeout = 4'd5;

        // Reset
        #20;
        rst = 0;
        enable = 1;

        // Normal operation: heartbeat/kick
        #20;
        kick = 1;
        #10;
        kick = 0;

        // Allow counter to run
        #20;

        // Another heartbeat
        kick = 1;
        #10;
        kick = 0;

        // Stop heartbeat and wait for timeout
        #80;

        if (wdt_reset)
            $display("WATCHDOG TIMEOUT DETECTED - PASS");
        else
            $display("WATCHDOG TIMEOUT NOT DETECTED - FAIL");

        $finish;
    end

endmodule

sim/dump.vcd
$date
	Thu Oct  8 18:55:22 2026
$end
$version
	Icarus Verilog
$end
$timescale
	1ps
$end
$scope module tb $end
$var wire 1 ! wdt_reset $end
$var wire 4 " count [3:0] $end
$var reg 1 # clk $end
$var reg 1 $ enable $end
$var reg 1 % kick $end
$var reg 1 & rst $end
$var reg 4 ' timeout [3:0] $end
$scope module dut $end
$var wire 1 # clk $end
$var wire 1 $ enable $end
$var wire 1 % kick $end
$var wire 1 & rst $end
$var wire 4 ( timeout [3:0] $end
$var parameter 32 ) TIMEOUT_WIDTH $end
$var reg 4 * count [3:0] $end
$var reg 1 ! wdt_reset $end
$upscope $end
$upscope $end
$enddefinitions $end
$comment Show the parameter values. $end
$dumpall
b100 )
$end
#0
$dumpvars
bx *
b101 (
b101 '
1&
0%
0$
0#
bx "
x!
$end
#5000
0!
b0 "
b0 *
1#
#10000
0#
#15000
1#
#20000
0#
1$
0&
#25000
b1 "
b1 *
1#
#30000
0#
#35000
b10 "
b10 *
1#
#40000
0#
1%
#45000
b0 "
b0 *
1#
#50000
0#
0%
#55000
b1 "
b1 *
1#
#60000
0#
#65000
b10 "
b10 *
1#
#70000
0#
1%
#75000
b0 "
b0 *
1#
#80000
0#
0%
#85000
b1 "
b1 *
1#
#90000
0#
#95000
b10 "
b10 *
1#
#100000
0#
#105000
b11 "
b11 *
1#
#110000
0#
#115000
b100 "
b100 *
1#
#120000
0#
#125000
b101 "
b101 *
1#
#130000
0#
#135000
1!
1#
